module/__init__.py
module/core.py
module_5mlet/__init__.py
module_5mlet/core.py
module_5mlet/investments.py
module_5mlet_package-2.0.0.dist-info/METADATA
module_5mlet_package-2.0.0.dist-info/WHEEL
module_5mlet_package-2.0.0.dist-info/top_level.txt
module_5mlet_package-2.0.0.dist-info/RECORD
