Metadata-Version: 2.4
Name: module-5mlet-package
Version: 2.0.0
Summary: Descrição da biblioteca Module 5MLET
Home-page: https://github.com/devrictrovato/postech-5mlet
Author: Ricardo O. Trovato
Author-email: devrictrovato@gmail.com
License: MIT
Classifier: Programming Language :: Python :: 3
Classifier: License :: OSI Approved :: MIT License
Requires-Python: >=3.6
Dynamic: author
Dynamic: author-email
Dynamic: classifier
Dynamic: description
Dynamic: description-content-type
Dynamic: home-page
Dynamic: license
Dynamic: requires-python
Dynamic: summary
